GMMchi/GMMchi.py
GMMchi/GMMchi_func.py
GMMchi/__init__.py
GMMchi/dynamic_binning.py
GMMchi/find_hits.py
GMMchi/probe_filter.py
GMMchi/run_hit_func.py
GMMchi/solve_gaussians.py
GMMchi-0.1.dist-info/LICENSE
GMMchi-0.1.dist-info/METADATA
GMMchi-0.1.dist-info/WHEEL
GMMchi-0.1.dist-info/top_level.txt
GMMchi-0.1.dist-info/RECORD
