Metadata-Version: 2.1
Name: GMMchi
Version: 0.1
Summary: GMM with chi-square protocol
Home-page: http://pypi.python.org/pypi/GMMchi/
Author: Jeff Liu
Author-email: jeffliu6068@gmail.com
License: MIT
Platform: UNKNOWN
Requires-Dist: pandas
Requires-Dist: scipy
Requires-Dist: numpy
Requires-Dist: matplotlib
Requires-Dist: seaborn
Requires-Dist: sklearn
Requires-Dist: tqdm
